questions/base_logic.v
module CRUDE_AWAKENING(
     input wire       in0,
     output wire       out
);
    assign out = in0;
endmodule

module NAND_GATE(
     input wire       in0,
     input wire       in1,
     output wire       out
);
    assign out = ~ ( in0 & in1 );
endmodule

module NOT_GATE(
     input wire       in0,
     output wire       out
);
    NAND_GATE NAND(
        .in0    (in0    ),
        .in1    (in0    ),
        .out    (out    )
    );
endmodule

module AND_GATE(
     input wire       in0,
     input wire       in1,
     output wire       out
);
    wire w_1;
    NAND_GATE NAND(
        .in0    (in0    ),
        .in1    (in1    ),
        .out    (w_1    )
    );

    NOT_GATE NOT(
        .in0    (w_1    ),
        .out    (out    )
    );
    
endmodule

module NOR_GATE(
     input wire       in0,
     input wire       in1,
     output wire       out
);
    wire w_0;
    wire w_1;
    wire n_out;
    NOT_GATE NOT0(
        .in0    (in0    ),
        .out    (w_0    )
    );
    NOT_GATE NOT1(
        .in0    (in1    ),
        .out    (w_1    )
    );
    NAND_GATE NAND(
        .in0    (w_0    ),
        .in1    (w_1    ),
        .out    (n_out    )
    );
    NOT_GATE NOT(
        .in0    (n_out    ),
        .out    (out    )
    );
endmodule

module OR_GATE(
     input wire       in0,
     input wire       in1,
     output wire       out
);
    wire w_0;
    wire w_1;
    NOT_GATE NOT0(
        .in0    (in0    ),
        .out    (w_0    )
    );
    NOT_GATE NOT1(
        .in0    (in1    ),
        .out    (w_1    )
    );
    NAND_GATE NAND(
        .in0    (w_0    ),
        .in1    (w_1    ),
        .out    (out    )
    );
endmodule

module ALWAYS_ON_GATE(
     input wire       in0,
     output wire       out
);
    wire w_1;
    NOT_GATE NOT(
        .in0    (in0    ),
        .out    (w_1    )
    );
    OR_GATE OR(
        .in0    (in0    ),
        .in1    (w_1    ),
        .out    (out    )
    );
endmodule

module SECOND_TICK(
     input wire       in0,
     input wire       in1,
     output wire       out
);
    wire w_0;
    wire n_out;
    NOT_GATE NOT(
        .in0    (in1    ),
        .out    (w_0    )
    );
    AND_GATE AND(
        .in0    (w_0    ),
        .in1    (in0    ),
        .out    (out    )
    );
endmodule

module XOR_GATE(
     input wire       in0,
     input wire       in1,
     output wire       out
);
    wire w_0;
    wire w_1;
    
    NOR_GATE NOR0(
        .in0    (in0    ),
        .in1    (in1    ),
        .out    (w_0    )
    );

    AND_GATE AND(
        .in0    (in0    ),
        .in1    (in1    ),
        .out    (w_1    )
    );
    NOR_GATE NOR1(
        .in0    (w_0    ),
        .in1    (w_1    ),
        .out    (out    )
    );

    
endmodule

module BIGGER_OR_GATE(
     input wire       in0,
     input wire       in1,
     input wire       in2,
     output wire       out
);
    wire w_0;
    wire w_1;
    
    OR_GATE OR0(
        .in0    (in0    ),
        .in1    (in1    ),
        .out    (w_0    )
    );

    OR_GATE OR1(
        .in0    (in1    ),
        .in1    (in2    ),
        .out    (w_1    )
    );
    OR_GATE OR2(
        .in0    (w_0    ),
        .in1    (w_1    ),
        .out    (out    )
    );

    
endmodule

module BIGGER_AND_GATE(
     input wire       in0,
     input wire       in1,
     input wire       in2,
     output wire       out
);
    wire w_0;
    wire w_1;
    
    AND_GATE AND0(
        .in0    (in0    ),
        .in1    (in1    ),
        .out    (w_0    )
    );

    AND_GATE AND1(
        .in0    (in1    ),
        .in1    (in2    ),
        .out    (w_1    )
    );
    AND_GATE AND2(
        .in0    (w_0    ),
        .in1    (w_1    ),
        .out    (out    )
    );

endmodule

module XNOR_GATE(
     input wire       in0,
     input wire       in1,
     output wire       out
);
    wire n_out;
    XOR_GATE XOR(
        .in0    (in0    ),
        .in1    (in1    ),
        .out    (n_out    )
    );
    NOT_GATE NOT(
        .in0    (n_out    ),
        .out    (out    )
    );
endmodule

questions/ARITHMETIC/03-2-FULL-ADDER/impl.v
module FULL_ADDER(
     input wire       in0,
     input wire       in1,
     input wire       in2,
     output wire     out,
     output wire cout
);
    wire w_0;
    wire w_1;
    wire w_2;
    XOR_GATE XOR0(
        .in0    (in0    ),
        .in1    (in1    ),
        .out    (w_0    )
    );
    XOR_GATE XOR1(
        .in0    (w_0    ),
        .in1    (in2    ),
        .out    (out    )
    );
    AND_GATE AND0(
        .in0    (in0    ),
        .in1    (in1    ),
        .out    (w_1    )
    );
    AND_GATE AND1(
        .in0    (w_0    ),
        .in1    (in2    ),
        .out    (w_2    )
    );
    OR_GATE OR0(
        .in0    (w_1    ),
        .in1    (w_2    ),
        .out    (cout    )
    );
    
endmodule

questions/ARITHMETIC/03-2-FULL-ADDER/tb.v
module FULL_ADDER_tb;

    reg in0 = 1'b0;
    reg in1 = 1'b0;
    reg in2 = 1'b0;
    initial begin
        $dumpfile("wave.vcd");
        $dumpvars(0, DUT);
    end
    
    FULL_ADDER DUT(
        .in0    (in0    ),
        .in1    (in1    ),
        .in2    (in2    ),
        .out    (out    ),
        .cout   (cout   )
    );

    initial begin
        in0 = 1'b0;
        in1 = 1'b0;
        in2 = 1'b0;
        #2
        in0 = 1'b1;
        in1 = 1'b0;
        in2 = 1'b0;
        #2
        in0 = 1'b0;
        in1 = 1'b1;
        in2 = 1'b0;
        #2
        in0 = 1'b1;
        in1 = 1'b1;
        in2 = 1'b0;
        #2
        in0 = 1'b0;
        in1 = 1'b0;
        in2 = 1'b1;
        #2
        in0 = 1'b1;
        in1 = 1'b0;
        in2 = 1'b1;
        #2
        in0 = 1'b0;
        in1 = 1'b1;
        in2 = 1'b1;
        #2
        in0 = 1'b1;
        in1 = 1'b1;
        in2 = 1'b1;
        #2
        $finish;
    end

endmodule

questions/ARITHMETIC/03-2-FULL-ADDER/wave.vcd
$date
	Sun Apr 21 07:14:17 2024
$end
$version
	Icarus Verilog
$end
$timescale
	1s
$end
$scope module FULL_ADDER_tb $end
$scope module DUT $end
$var wire 1 ! in0 $end
$var wire 1 " in1 $end
$var wire 1 # in2 $end
$var wire 1 $ w_2 $end
$var wire 1 % w_1 $end
$var wire 1 & w_0 $end
$var wire 1 ' out $end
$var wire 1 ( cout $end
$scope module AND0 $end
$var wire 1 ! in0 $end
$var wire 1 " in1 $end
$var wire 1 ) w_1 $end
$var wire 1 % out $end
$scope module NAND $end
$var wire 1 ! in0 $end
$var wire 1 " in1 $end
$var wire 1 ) out $end
$upscope $end
$scope module NOT $end
$var wire 1 ) in0 $end
$var wire 1 % out $end
$scope module NAND $end
$var wire 1 ) in0 $end
$var wire 1 ) in1 $end
$var wire 1 % out $end
$upscope $end
$upscope $end
$upscope $end
$scope module AND1 $end
$var wire 1 # in1 $end
$var wire 1 * w_1 $end
$var wire 1 $ out $end
$var wire 1 & in0 $end
$scope module NAND $end
$var wire 1 # in1 $end
$var wire 1 * out $end
$var wire 1 & in0 $end
$upscope $end
$scope module NOT $end
$var wire 1 * in0 $end
$var wire 1 $ out $end
$scope module NAND $end
$var wire 1 * in0 $end
$var wire 1 * in1 $end
$var wire 1 $ out $end
$upscope $end
$upscope $end
$upscope $end
$scope module OR0 $end
$var wire 1 % in0 $end
$var wire 1 $ in1 $end
$var wire 1 + w_1 $end
$var wire 1 , w_0 $end
$var wire 1 ( out $end
$scope module NAND $end
$var wire 1 ( out $end
$var wire 1 + in1 $end
$var wire 1 , in0 $end
$upscope $end
$scope module NOT0 $end
$var wire 1 % in0 $end
$var wire 1 , out $end
$scope module NAND $end
$var wire 1 % in0 $end
$var wire 1 % in1 $end
$var wire 1 , out $end
$upscope $end
$upscope $end
$scope module NOT1 $end
$var wire 1 $ in0 $end
$var wire 1 + out $end
$scope module NAND $end
$var wire 1 $ in0 $end
$var wire 1 $ in1 $end
$var wire 1 + out $end
$upscope $end
$upscope $end
$upscope $end
$scope module XOR0 $end
$var wire 1 ! in0 $end
$var wire 1 " in1 $end
$var wire 1 - w_1 $end
$var wire 1 . w_0 $end
$var wire 1 & out $end
$scope module AND $end
$var wire 1 ! in0 $end
$var wire 1 " in1 $end
$var wire 1 / w_1 $end
$var wire 1 - out $end
$scope module NAND $end
$var wire 1 ! in0 $end
$var wire 1 " in1 $end
$var wire 1 / out $end
$upscope $end
$scope module NOT $end
$var wire 1 / in0 $end
$var wire 1 - out $end
$scope module NAND $end
$var wire 1 / in0 $end
$var wire 1 / in1 $end
$var wire 1 - out $end
$upscope $end
$upscope $end
$upscope $end
$scope module NOR0 $end
$var wire 1 ! in0 $end
$var wire 1 " in1 $end
$var wire 1 0 w_1 $end
$var wire 1 1 w_0 $end
$var wire 1 . out $end
$var wire 1 2 n_out $end
$scope module NAND $end
$var wire 1 2 out $end
$var wire 1 0 in1 $end
$var wire 1 1 in0 $end
$upscope $end
$scope module NOT $end
$var wire 1 2 in0 $end
$var wire 1 . out $end
$scope module NAND $end
$var wire 1 2 in0 $end
$var wire 1 2 in1 $end
$var wire 1 . out $end
$upscope $end
$upscope $end
$scope module NOT0 $end
$var wire 1 ! in0 $end
$var wire 1 1 out $end
$scope module NAND $end
$var wire 1 ! in0 $end
$var wire 1 ! in1 $end
$var wire 1 1 out $end
$upscope $end
$upscope $end
$scope module NOT1 $end
$var wire 1 " in0 $end
$var wire 1 0 out $end
$scope module NAND $end
$var wire 1 " in0 $end
$var wire 1 " in1 $end
$var wire 1 0 out $end
$upscope $end
$upscope $end
$upscope $end
$scope module NOR1 $end
$var wire 1 . in0 $end
$var wire 1 - in1 $end
$var wire 1 3 w_1 $end
$var wire 1 4 w_0 $end
$var wire 1 & out $end
$var wire 1 5 n_out $end
$scope module NAND $end
$var wire 1 5 out $end
$var wire 1 3 in1 $end
$var wire 1 4 in0 $end
$upscope $end
$scope module NOT $end
$var wire 1 5 in0 $end
$var wire 1 & out $end
$scope module NAND $end
$var wire 1 5 in0 $end
$var wire 1 5 in1 $end
$var wire 1 & out $end
$upscope $end
$upscope $end
$scope module NOT0 $end
$var wire 1 . in0 $end
$var wire 1 4 out $end
$scope module NAND $end
$var wire 1 . in0 $end
$var wire 1 . in1 $end
$var wire 1 4 out $end
$upscope $end
$upscope $end
$scope module NOT1 $end
$var wire 1 - in0 $end
$var wire 1 3 out $end
$scope module NAND $end
$var wire 1 - in0 $end
$var wire 1 - in1 $end
$var wire 1 3 out $end
$upscope $end
$upscope $end
$upscope $end
$upscope $end
$scope module XOR1 $end
$var wire 1 & in0 $end
$var wire 1 # in1 $end
$var wire 1 6 w_1 $end
$var wire 1 7 w_0 $end
$var wire 1 ' out $end
$scope module AND $end
$var wire 1 & in0 $end
$var wire 1 # in1 $end
$var wire 1 8 w_1 $end
$var wire 1 6 out $end
$scope module NAND $end
$var wire 1 & in0 $end
$var wire 1 # in1 $end
$var wire 1 8 out $end
$upscope $end
$scope module NOT $end
$var wire 1 8 in0 $end
$var wire 1 6 out $end
$scope module NAND $end
$var wire 1 8 in0 $end
$var wire 1 8 in1 $end
$var wire 1 6 out $end
$upscope $end
$upscope $end
$upscope $end
$scope module NOR0 $end
$var wire 1 & in0 $end
$var wire 1 # in1 $end
$var wire 1 9 w_1 $end
$var wire 1 : w_0 $end
$var wire 1 7 out $end
$var wire 1 ; n_out $end
$scope module NAND $end
$var wire 1 ; out $end
$var wire 1 9 in1 $end
$var wire 1 : in0 $end
$upscope $end
$scope module NOT $end
$var wire 1 ; in0 $end
$var wire 1 7 out $end
$scope module NAND $end
$var wire 1 ; in0 $end
$var wire 1 ; in1 $end
$var wire 1 7 out $end
$upscope $end
$upscope $end
$scope module NOT0 $end
$var wire 1 & in0 $end
$var wire 1 : out $end
$scope module NAND $end
$var wire 1 & in0 $end
$var wire 1 & in1 $end
$var wire 1 : out $end
$upscope $end
$upscope $end
$scope module NOT1 $end
$var wire 1 # in0 $end
$var wire 1 9 out $end
$scope module NAND $end
$var wire 1 # in0 $end
$var wire 1 # in1 $end
$var wire 1 9 out $end
$upscope $end
$upscope $end
$upscope $end
$scope module NOR1 $end
$var wire 1 7 in0 $end
$var wire 1 6 in1 $end
$var wire 1 < w_1 $end
$var wire 1 = w_0 $end
$var wire 1 ' out $end
$var wire 1 > n_out $end
$scope module NAND $end
$var wire 1 > out $end
$var wire 1 < in1 $end
$var wire 1 = in0 $end
$upscope $end
$scope module NOT $end
$var wire 1 > in0 $end
$var wire 1 ' out $end
$scope module NAND $end
$var wire 1 > in0 $end
$var wire 1 > in1 $end
$var wire 1 ' out $end
$upscope $end
$upscope $end
$scope module NOT0 $end
$var wire 1 7 in0 $end
$var wire 1 = out $end
$scope module NAND $end
$var wire 1 7 in0 $end
$var wire 1 7 in1 $end
$var wire 1 = out $end
$upscope $end
$upscope $end
$scope module NOT1 $end
$var wire 1 6 in0 $end
$var wire 1 < out $end
$scope module NAND $end
$var wire 1 6 in0 $end
$var wire 1 6 in1 $end
$var wire 1 < out $end
$upscope $end
$upscope $end
$upscope $end
$upscope $end
$upscope $end
$upscope $end
$enddefinitions $end
$comment Show the parameter values. $end
$dumpall
$end
#0
$dumpvars
1>
0=
1<
0;
1:
19
18
17
06
15
04
13
02
11
10
1/
1.
0-
1,
1+
1*
1)
0(
0'
0&
0%
0$
0#
0"
0!
$end
#2
1'
0>
1=
07
1;
0:
1&
05
14
0.
12
01
1!
#4
00
11
1"
0!
#6
0'
1>
0=
17
0;
1:
0&
1(
15
0,
03
1%
1-
0)
0/
01
1!
#8
1<
1+
06
0$
1'
18
1:
1*
0>
0&
1=
0(
15
04
07
1,
13
1.
1;
0%
0-
02
09
10
1)
1/
11
1#
0"
0!
#10
0'
1>
1(
0<
0+
16
1$
08
0:
0*
1&
05
14
0.
12
01
1!
#12
00
11
1"
0!
#14
1'
0>
1<
1+
06
0$
18
1:
1*
0&
15
0,
03
1%
1-
0)
0/
01
1!
