questions/base_logic.v
module CRUDE_AWAKENING(
     input wire       in0,
     output wire       out
);
    assign out = in0;
endmodule

module NAND_GATE(
     input wire       in0,
     input wire       in1,
     output wire       out
);
    assign out = ~ ( in0 & in1 );
endmodule

module NOT_GATE(
     input wire       in0,
     output wire       out
);
    NAND_GATE NAND(
        .in0    (in0    ),
        .in1    (in0    ),
        .out    (out    )
    );
endmodule

module AND_GATE(
     input wire       in0,
     input wire       in1,
     output wire       out
);
    wire w_1;
    NAND_GATE NAND(
        .in0    (in0    ),
        .in1    (in1    ),
        .out    (w_1    )
    );

    NOT_GATE NOT(
        .in0    (w_1    ),
        .out    (out    )
    );
    
endmodule

module NOR_GATE(
     input wire       in0,
     input wire       in1,
     output wire       out
);
    wire w_0;
    wire w_1;
    wire n_out;
    NOT_GATE NOT0(
        .in0    (in0    ),
        .out    (w_0    )
    );
    NOT_GATE NOT1(
        .in0    (in1    ),
        .out    (w_1    )
    );
    NAND_GATE NAND(
        .in0    (w_0    ),
        .in1    (w_1    ),
        .out    (n_out    )
    );
    NOT_GATE NOT(
        .in0    (n_out    ),
        .out    (out    )
    );
endmodule

module OR_GATE(
     input wire       in0,
     input wire       in1,
     output wire       out
);
    wire w_0;
    wire w_1;
    NOT_GATE NOT0(
        .in0    (in0    ),
        .out    (w_0    )
    );
    NOT_GATE NOT1(
        .in0    (in1    ),
        .out    (w_1    )
    );
    NAND_GATE NAND(
        .in0    (w_0    ),
        .in1    (w_1    ),
        .out    (out    )
    );
endmodule

module ALWAYS_ON_GATE(
     input wire       in0,
     output wire       out
);
    wire w_1;
    NOT_GATE NOT(
        .in0    (in0    ),
        .out    (w_1    )
    );
    OR_GATE OR(
        .in0    (in0    ),
        .in1    (w_1    ),
        .out    (out    )
    );
endmodule

module SECOND_TICK(
     input wire       in0,
     input wire       in1,
     output wire       out
);
    wire w_0;
    wire n_out;
    NOT_GATE NOT(
        .in0    (in1    ),
        .out    (w_0    )
    );
    AND_GATE AND(
        .in0    (w_0    ),
        .in1    (in0    ),
        .out    (out    )
    );
endmodule

module XOR_GATE(
     input wire       in0,
     input wire       in1,
     output wire       out
);
    wire w_0;
    wire w_1;
    
    NOR_GATE NOR0(
        .in0    (in0    ),
        .in1    (in1    ),
        .out    (w_0    )
    );

    AND_GATE AND(
        .in0    (in0    ),
        .in1    (in1    ),
        .out    (w_1    )
    );
    NOR_GATE NOR1(
        .in0    (w_0    ),
        .in1    (w_1    ),
        .out    (out    )
    );

    
endmodule

module BIGGER_OR_GATE(
     input wire       in0,
     input wire       in1,
     input wire       in2,
     output wire       out
);
    wire w_0;
    wire w_1;
    
    OR_GATE OR0(
        .in0    (in0    ),
        .in1    (in1    ),
        .out    (w_0    )
    );

    OR_GATE OR1(
        .in0    (in1    ),
        .in1    (in2    ),
        .out    (w_1    )
    );
    OR_GATE OR2(
        .in0    (w_0    ),
        .in1    (w_1    ),
        .out    (out    )
    );

    
endmodule

module BIGGER_AND_GATE(
     input wire       in0,
     input wire       in1,
     input wire       in2,
     output wire       out
);
    wire w_0;
    wire w_1;
    
    AND_GATE AND0(
        .in0    (in0    ),
        .in1    (in1    ),
        .out    (w_0    )
    );

    AND_GATE AND1(
        .in0    (in1    ),
        .in1    (in2    ),
        .out    (w_1    )
    );
    AND_GATE AND2(
        .in0    (w_0    ),
        .in1    (w_1    ),
        .out    (out    )
    );

endmodule

module XNOR_GATE(
     input wire       in0,
     input wire       in1,
     output wire       out
);
    wire n_out;
    XOR_GATE XOR(
        .in0    (in0    ),
        .in1    (in1    ),
        .out    (n_out    )
    );
    NOT_GATE NOT(
        .in0    (n_out    ),
        .out    (out    )
    );
endmodule

module SWITCH_GATE(
    input wire clk,
    input wire in0,
    input wire in1,
    output reg out
);

initial @ (posedge clk) begin
    if (in0 > 1'b0) begin
    assign out = in1;
    end else begin
    assign out = 1'b0;
    end
end

endmodule

module BYTE_SWITCH_GATE(
    input wire clk,
    input wire in0,
    input wire [7:0] in1,
    output reg [7:0] out
);
always @(posedge clk) begin
     if(in0>1'b0) begin 
        assign out = in1;
    end else begin
        assign out = 8'b00000000;
    end
end

endmodule

questions/MEMORY/05-INPUT-SELECTOR/impl.v
module MUX(
    input wire clk,
     input wire swc,
     input wire [7:0] in0,
     input wire [7:0] in1,
     output reg [7:0] out
);
wire w_0;
wire [7:0]w_1;
wire [7:0]w_2;
NOT_GATE NOT(
    .in0    (swc    ),
    .out    (w_0    )
);

BYTE_SWITCH_GATE BYTE_SWITCH_GATE_0(
    .clk    (clk    ),
    .in0    (swc    ),
    .in1    (in0    ),
    .out    (w_1    )
);


BYTE_SWITCH_GATE BYTE_SWITCH_GATE_1(
    .clk    (clk    ),
    .in0    (w_0    ),
    .in1    (in1    ),
    .out    (w_2    )
);
always @(posedge clk) begin
      if (swc > 1'b0) begin
        assign out = w_1;
        end else begin
        assign out = w_2;
        end 
end

endmodule

questions/MEMORY/05-INPUT-SELECTOR/tb.v
module MUX_tb;
    reg clk = 1'b0;
    reg       swc = 1'b0;
    reg    [7:0]    in0 = 8'h00;
    reg    [7:0]    in1 = 8'h00;
    wire   [7:0]    out;
    
initial begin
        $dumpfile("wave.vcd");
        $dumpvars(0, DUT);
    end
    always #1 begin
        clk <= ~clk;
    end

    MUX DUT(
        .clk    (clk    ),
        .swc    (swc    ),
        .in0    (in0    ),
        .in1    (in1    ),
        .out    (out    )
    );
    
    initial begin
        #2
        in0 = 8'h01;
        in1 = 8'h01;
        #2
        in0 = 8'h01;
        in1 = 8'h02;
        #2
        swc = 1'b1;
        in0 = 8'h05;
        in1 = 8'h10;
        #2
        in0 = 8'h10;
        in1 = 8'h08;
        #2
        swc = 1'b0;
        in0 = 8'hff;
        in1 = 8'hf0;
        #2
        $finish;
    end
endmodule

questions/MEMORY/05-INPUT-SELECTOR/wave.vcd
$date
	Fri Apr 26 11:15:42 2024
$end
$version
	Icarus Verilog
$end
$timescale
	1s
$end
$scope module MUX_tb $end
$scope module DUT $end
$var wire 1 ! clk $end
$var wire 8 " in0 [7:0] $end
$var wire 8 # in1 [7:0] $end
$var wire 1 $ swc $end
$var wire 8 % w_2 [7:0] $end
$var wire 8 & w_1 [7:0] $end
$var wire 1 ' w_0 $end
$var reg 8 ( out [7:0] $end
$scope module BYTE_SWITCH_GATE_0 $end
$var wire 1 ! clk $end
$var wire 1 $ in0 $end
$var wire 8 ) in1 [7:0] $end
$var reg 8 * out [7:0] $end
$upscope $end
$scope module BYTE_SWITCH_GATE_1 $end
$var wire 1 ! clk $end
$var wire 8 + in1 [7:0] $end
$var wire 1 ' in0 $end
$var reg 8 , out [7:0] $end
$upscope $end
$scope module NOT $end
$var wire 1 $ in0 $end
$var wire 1 ' out $end
$scope module NAND $end
$var wire 1 $ in0 $end
$var wire 1 $ in1 $end
$var wire 1 ' out $end
$upscope $end
$upscope $end
$upscope $end
$upscope $end
$enddefinitions $end
$comment Show the parameter values. $end
$dumpall
$end
#0
$dumpvars
bx ,
b0 +
bx *
b0 )
bx (
1'
bx &
bx %
0$
b0 #
b0 "
0!
$end
#1
b0 &
b0 *
b0 (
b0 %
b0 ,
1!
#2
0!
b1 (
b1 %
b1 ,
b1 #
b1 +
b1 "
b1 )
#3
1!
#4
0!
b10 (
b10 %
b10 ,
b10 #
b10 +
#5
1!
#6
0!
0'
b10000 (
b10000 %
b10000 ,
b10000 #
b10000 +
b101 "
b101 )
1$
#7
b101 (
b0 %
b0 ,
b101 &
b101 *
1!
#8
0!
b1000 #
b1000 +
b10000 (
b10000 &
b10000 *
b10000 "
b10000 )
#9
1!
#10
0!
1'
b11110000 #
b11110000 +
b11111111 (
b11111111 &
b11111111 *
b11111111 "
b11111111 )
0$
#11
b11110000 %
b11110000 ,
b11110000 (
b0 &
b0 *
1!
