questions/base_logic.v
module CRUDE_AWAKENING(
     input wire       in0,
     output wire       out
);
    assign out = in0;
endmodule

module NAND_GATE(
     input wire       in0,
     input wire       in1,
     output wire       out
);
    assign out = ~ ( in0 & in1 );
endmodule

module NOT_GATE(
     input wire       in0,
     output wire       out
);
    NAND_GATE NAND(
        .in0    (in0    ),
        .in1    (in0    ),
        .out    (out    )
    );
endmodule

module AND_GATE(
     input wire       in0,
     input wire       in1,
     output wire       out
);
    wire w_1;
    NAND_GATE NAND(
        .in0    (in0    ),
        .in1    (in1    ),
        .out    (w_1    )
    );

    NOT_GATE NOT(
        .in0    (w_1    ),
        .out    (out    )
    );
    
endmodule

module NOR_GATE(
     input wire       in0,
     input wire       in1,
     output wire       out
);
    wire w_0;
    wire w_1;
    wire n_out;
    NOT_GATE NOT0(
        .in0    (in0    ),
        .out    (w_0    )
    );
    NOT_GATE NOT1(
        .in0    (in1    ),
        .out    (w_1    )
    );
    NAND_GATE NAND(
        .in0    (w_0    ),
        .in1    (w_1    ),
        .out    (n_out    )
    );
    NOT_GATE NOT(
        .in0    (n_out    ),
        .out    (out    )
    );
endmodule

module OR_GATE(
     input wire       in0,
     input wire       in1,
     output wire       out
);
    wire w_0;
    wire w_1;
    NOT_GATE NOT0(
        .in0    (in0    ),
        .out    (w_0    )
    );
    NOT_GATE NOT1(
        .in0    (in1    ),
        .out    (w_1    )
    );
    NAND_GATE NAND(
        .in0    (w_0    ),
        .in1    (w_1    ),
        .out    (out    )
    );
endmodule

module ALWAYS_ON_GATE(
     input wire       in0,
     output wire       out
);
    wire w_1;
    NOT_GATE NOT(
        .in0    (in0    ),
        .out    (w_1    )
    );
    OR_GATE OR(
        .in0    (in0    ),
        .in1    (w_1    ),
        .out    (out    )
    );
endmodule

module SECOND_TICK(
     input wire       in0,
     input wire       in1,
     output wire       out
);
    wire w_0;
    wire n_out;
    NOT_GATE NOT(
        .in0    (in1    ),
        .out    (w_0    )
    );
    AND_GATE AND(
        .in0    (w_0    ),
        .in1    (in0    ),
        .out    (out    )
    );
endmodule

module XOR_GATE(
     input wire       in0,
     input wire       in1,
     output wire       out
);
    wire w_0;
    wire w_1;
    
    NOR_GATE NOR0(
        .in0    (in0    ),
        .in1    (in1    ),
        .out    (w_0    )
    );

    AND_GATE AND(
        .in0    (in0    ),
        .in1    (in1    ),
        .out    (w_1    )
    );
    NOR_GATE NOR1(
        .in0    (w_0    ),
        .in1    (w_1    ),
        .out    (out    )
    );

    
endmodule

module BIGGER_OR_GATE(
     input wire       in0,
     input wire       in1,
     input wire       in2,
     output wire       out
);
    wire w_0;
    wire w_1;
    
    OR_GATE OR0(
        .in0    (in0    ),
        .in1    (in1    ),
        .out    (w_0    )
    );

    OR_GATE OR1(
        .in0    (in1    ),
        .in1    (in2    ),
        .out    (w_1    )
    );
    OR_GATE OR2(
        .in0    (w_0    ),
        .in1    (w_1    ),
        .out    (out    )
    );

    
endmodule

module BIGGER_AND_GATE(
     input wire       in0,
     input wire       in1,
     input wire       in2,
     output wire       out
);
    wire w_0;
    wire w_1;
    
    AND_GATE AND0(
        .in0    (in0    ),
        .in1    (in1    ),
        .out    (w_0    )
    );

    AND_GATE AND1(
        .in0    (in1    ),
        .in1    (in2    ),
        .out    (w_1    )
    );
    AND_GATE AND2(
        .in0    (w_0    ),
        .in1    (w_1    ),
        .out    (out    )
    );

endmodule

module XNOR_GATE(
     input wire       in0,
     input wire       in1,
     output wire       out
);
    wire n_out;
    XOR_GATE XOR(
        .in0    (in0    ),
        .in1    (in1    ),
        .out    (n_out    )
    );
    NOT_GATE NOT(
        .in0    (n_out    ),
        .out    (out    )
    );
endmodule

questions/ARITHMETIC/01-1-DOUBLE-TROUBLE/impl.v
module  DOUBLE_TROUBLE(
     input wire       in0,
     input wire       in1,
     input wire       in2,
     input wire       in3,
     output wire       out
);
    wire w_0;
    wire w_1;
    wire w_2;
    wire w_3;
    wire w_4;
    wire w_5;
    wire w_out0;
    wire w_out1;
    
    AND_GATE AND0(
        .in0    (in0    ),
        .in1    (in1    ),
        .out    (w_0    )
    );

    AND_GATE AND1(
        .in0    (in0    ),
        .in1    (in2    ),
        .out    (w_1    )
    );
    AND_GATE AND2(
        .in0    (in0    ),
        .in1    (in3    ),
        .out    (w_2    )
    );
    AND_GATE AND3(
        .in0    (in1    ),
        .in1    (in2    ),
        .out    (w_3    )
    );

    AND_GATE AND4(
        .in0    (in1    ),
        .in1    (in3    ),
        .out    (w_4    )
    );
    AND_GATE AND5(
        .in0    (in2    ),
        .in1    (in3    ),
        .out    (w_5    )
    );
    BIGGER_OR_GATE BIGOR0(
        .in0    (w_0    ),
        .in1    (w_1    ),
        .in2    (w_2    ),
        .out    (w_out0    )
    );
    BIGGER_OR_GATE BIGOR1(
        .in0    (w_3    ),
        .in1    (w_4    ),
        .in2    (w_5    ),
        .out    (w_out1    )
    );
    OR_GATE OR0(
        .in0    (w_out0    ),
        .in1    (w_out1    ),
        .out    (out    )
    );
    
endmodule

questions/ARITHMETIC/01-DOUBLE-TROUBLE/tb.V
module DOUBLE_TROUBLE_tb;

    reg in0 = 1'b0;
    reg in1 = 1'b0;
    reg in2 = 1'b0;
    reg in3 = 1'b0;

    initial begin
        $dumpfile("wave.vcd");
        $dumpvars(0, DUT);
    end
    
    DOUBLE_TROUBLE DUT(
        .in0    (in0    ),
        .in1    (in1    ),
        .in2    (in2    ),
        .in3    (in3    ),
        .out    (out    )
    );

    initial begin
        in0 = 1'b0;
        in1 = 1'b0;
        in2 = 1'b0;
        in3 = 1'b0;
        #2
        in0 = 1'b1;
        in1 = 1'b0;
        in2 = 1'b0;
        in3 = 1'b0;
        #2
        in0 = 1'b0;
        in1 = 1'b1;
        in2 = 1'b0;
        in3 = 1'b0;
        #2
        in0 = 1'b1;
        in1 = 1'b1;
        in2 = 1'b0;
        in3 = 1'b0;
        #2
        in0 = 1'b0;
        in1 = 1'b0;
        in2 = 1'b1;
        in3 = 1'b0;
        #2
        in0 = 1'b1;
        in1 = 1'b0;
        in2 = 1'b1;
        in3 = 1'b0;
        #2
        in0 = 1'b0;
        in1 = 1'b1;
        in2 = 1'b1;
        in3 = 1'b0;
        #2
        in0 = 1'b1;
        in1 = 1'b1;
        in2 = 1'b1;
        in3 = 1'b0;
        #2
        in0 = 1'b0;
        in1 = 1'b0;
        in2 = 1'b0;
        in3 = 1'b1;
        #2
        in0 = 1'b1;
        in1 = 1'b0;
        in2 = 1'b0;
        in3 = 1'b1;
        #2
        in0 = 1'b0;
        in1 = 1'b1;
        in2 = 1'b0;
        in3 = 1'b1;
        #2
        in0 = 1'b1;
        in1 = 1'b1;
        in2 = 1'b0;
        in3 = 1'b1;
        #2
        in0 = 1'b0;
        in1 = 1'b0;
        in2 = 1'b1;
        in3 = 1'b1;
        #2
        in0 = 1'b1;
        in1 = 1'b0;
        in2 = 1'b1;
        in3 = 1'b1;
        #2
        in0 = 1'b0;
        in1 = 1'b1;
        in2 = 1'b1;
        in3 = 1'b1;
        #2
        in0 = 1'b1;
        in1 = 1'b1;
        in2 = 1'b1;
        in3 = 1'b1;
        #2
        $finish;
    end

endmodule

questions/ARITHMETIC/01-1-DOUBLE-TROUBLE/wave.vcd
$date
	Wed Apr 17 17:41:36 2024
$end
$version
	Icarus Verilog
$end
$timescale
	1s
$end
$scope module DOUBLE_TROUBLE_tb $end
$scope module DUT $end
$var wire 1 ! in0 $end
$var wire 1 " in1 $end
$var wire 1 # in2 $end
$var wire 1 $ in3 $end
$var wire 1 % w_out1 $end
$var wire 1 & w_out0 $end
$var wire 1 ' w_5 $end
$var wire 1 ( w_4 $end
$var wire 1 ) w_3 $end
$var wire 1 * w_2 $end
$var wire 1 + w_1 $end
$var wire 1 , w_0 $end
$var wire 1 - out $end
$scope module AND0 $end
$var wire 1 ! in0 $end
$var wire 1 " in1 $end
$var wire 1 . w_1 $end
$var wire 1 , out $end
$scope module NAND $end
$var wire 1 ! in0 $end
$var wire 1 " in1 $end
$var wire 1 . out $end
$upscope $end
$scope module NOT $end
$var wire 1 . in0 $end
$var wire 1 , out $end
$scope module NAND $end
$var wire 1 . in0 $end
$var wire 1 . in1 $end
$var wire 1 , out $end
$upscope $end
$upscope $end
$upscope $end
$scope module AND1 $end
$var wire 1 ! in0 $end
$var wire 1 # in1 $end
$var wire 1 / w_1 $end
$var wire 1 + out $end
$scope module NAND $end
$var wire 1 ! in0 $end
$var wire 1 # in1 $end
$var wire 1 / out $end
$upscope $end
$scope module NOT $end
$var wire 1 / in0 $end
$var wire 1 + out $end
$scope module NAND $end
$var wire 1 / in0 $end
$var wire 1 / in1 $end
$var wire 1 + out $end
$upscope $end
$upscope $end
$upscope $end
$scope module AND2 $end
$var wire 1 ! in0 $end
$var wire 1 $ in1 $end
$var wire 1 0 w_1 $end
$var wire 1 * out $end
$scope module NAND $end
$var wire 1 ! in0 $end
$var wire 1 $ in1 $end
$var wire 1 0 out $end
$upscope $end
$scope module NOT $end
$var wire 1 0 in0 $end
$var wire 1 * out $end
$scope module NAND $end
$var wire 1 0 in0 $end
$var wire 1 0 in1 $end
$var wire 1 * out $end
$upscope $end
$upscope $end
$upscope $end
$scope module AND3 $end
$var wire 1 " in0 $end
$var wire 1 # in1 $end
$var wire 1 1 w_1 $end
$var wire 1 ) out $end
$scope module NAND $end
$var wire 1 " in0 $end
$var wire 1 # in1 $end
$var wire 1 1 out $end
$upscope $end
$scope module NOT $end
$var wire 1 1 in0 $end
$var wire 1 ) out $end
$scope module NAND $end
$var wire 1 1 in0 $end
$var wire 1 1 in1 $end
$var wire 1 ) out $end
$upscope $end
$upscope $end
$upscope $end
$scope module AND4 $end
$var wire 1 " in0 $end
$var wire 1 $ in1 $end
$var wire 1 2 w_1 $end
$var wire 1 ( out $end
$scope module NAND $end
$var wire 1 " in0 $end
$var wire 1 $ in1 $end
$var wire 1 2 out $end
$upscope $end
$scope module NOT $end
$var wire 1 2 in0 $end
$var wire 1 ( out $end
$scope module NAND $end
$var wire 1 2 in0 $end
$var wire 1 2 in1 $end
$var wire 1 ( out $end
$upscope $end
$upscope $end
$upscope $end
$scope module AND5 $end
$var wire 1 # in0 $end
$var wire 1 $ in1 $end
$var wire 1 3 w_1 $end
$var wire 1 ' out $end
$scope module NAND $end
$var wire 1 # in0 $end
$var wire 1 $ in1 $end
$var wire 1 3 out $end
$upscope $end
$scope module NOT $end
$var wire 1 3 in0 $end
$var wire 1 ' out $end
$scope module NAND $end
$var wire 1 3 in0 $end
$var wire 1 3 in1 $end
$var wire 1 ' out $end
$upscope $end
$upscope $end
$upscope $end
$scope module BIGOR0 $end
$var wire 1 , in0 $end
$var wire 1 + in1 $end
$var wire 1 * in2 $end
$var wire 1 4 w_1 $end
$var wire 1 5 w_0 $end
$var wire 1 & out $end
$scope module OR0 $end
$var wire 1 , in0 $end
$var wire 1 + in1 $end
$var wire 1 6 w_1 $end
$var wire 1 7 w_0 $end
$var wire 1 5 out $end
$scope module NAND $end
$var wire 1 5 out $end
$var wire 1 6 in1 $end
$var wire 1 7 in0 $end
$upscope $end
$scope module NOT0 $end
$var wire 1 , in0 $end
$var wire 1 7 out $end
$scope module NAND $end
$var wire 1 , in0 $end
$var wire 1 , in1 $end
$var wire 1 7 out $end
$upscope $end
$upscope $end
$scope module NOT1 $end
$var wire 1 + in0 $end
$var wire 1 6 out $end
$scope module NAND $end
$var wire 1 + in0 $end
$var wire 1 + in1 $end
$var wire 1 6 out $end
$upscope $end
$upscope $end
$upscope $end
$scope module OR1 $end
$var wire 1 + in0 $end
$var wire 1 * in1 $end
$var wire 1 8 w_1 $end
$var wire 1 9 w_0 $end
$var wire 1 4 out $end
$scope module NAND $end
$var wire 1 4 out $end
$var wire 1 8 in1 $end
$var wire 1 9 in0 $end
$upscope $end
$scope module NOT0 $end
$var wire 1 + in0 $end
$var wire 1 9 out $end
$scope module NAND $end
$var wire 1 + in0 $end
$var wire 1 + in1 $end
$var wire 1 9 out $end
$upscope $end
$upscope $end
$scope module NOT1 $end
$var wire 1 * in0 $end
$var wire 1 8 out $end
$scope module NAND $end
$var wire 1 * in0 $end
$var wire 1 * in1 $end
$var wire 1 8 out $end
$upscope $end
$upscope $end
$upscope $end
$scope module OR2 $end
$var wire 1 5 in0 $end
$var wire 1 4 in1 $end
$var wire 1 : w_1 $end
$var wire 1 ; w_0 $end
$var wire 1 & out $end
$scope module NAND $end
$var wire 1 & out $end
$var wire 1 : in1 $end
$var wire 1 ; in0 $end
$upscope $end
$scope module NOT0 $end
$var wire 1 5 in0 $end
$var wire 1 ; out $end
$scope module NAND $end
$var wire 1 5 in0 $end
$var wire 1 5 in1 $end
$var wire 1 ; out $end
$upscope $end
$upscope $end
$scope module NOT1 $end
$var wire 1 4 in0 $end
$var wire 1 : out $end
$scope module NAND $end
$var wire 1 4 in0 $end
$var wire 1 4 in1 $end
$var wire 1 : out $end
$upscope $end
$upscope $end
$upscope $end
$upscope $end
$scope module BIGOR1 $end
$var wire 1 ) in0 $end
$var wire 1 ( in1 $end
$var wire 1 ' in2 $end
$var wire 1 < w_1 $end
$var wire 1 = w_0 $end
$var wire 1 % out $end
$scope module OR0 $end
$var wire 1 ) in0 $end
$var wire 1 ( in1 $end
$var wire 1 > w_1 $end
$var wire 1 ? w_0 $end
$var wire 1 = out $end
$scope module NAND $end
$var wire 1 = out $end
$var wire 1 > in1 $end
$var wire 1 ? in0 $end
$upscope $end
$scope module NOT0 $end
$var wire 1 ) in0 $end
$var wire 1 ? out $end
$scope module NAND $end
$var wire 1 ) in0 $end
$var wire 1 ) in1 $end
$var wire 1 ? out $end
$upscope $end
$upscope $end
$scope module NOT1 $end
$var wire 1 ( in0 $end
$var wire 1 > out $end
$scope module NAND $end
$var wire 1 ( in0 $end
$var wire 1 ( in1 $end
$var wire 1 > out $end
$upscope $end
$upscope $end
$upscope $end
$scope module OR1 $end
$var wire 1 ( in0 $end
$var wire 1 ' in1 $end
$var wire 1 @ w_1 $end
$var wire 1 A w_0 $end
$var wire 1 < out $end
$scope module NAND $end
$var wire 1 < out $end
$var wire 1 @ in1 $end
$var wire 1 A in0 $end
$upscope $end
$scope module NOT0 $end
$var wire 1 ( in0 $end
$var wire 1 A out $end
$scope module NAND $end
$var wire 1 ( in0 $end
$var wire 1 ( in1 $end
$var wire 1 A out $end
$upscope $end
$upscope $end
$scope module NOT1 $end
$var wire 1 ' in0 $end
$var wire 1 @ out $end
$scope module NAND $end
$var wire 1 ' in0 $end
$var wire 1 ' in1 $end
$var wire 1 @ out $end
$upscope $end
$upscope $end
$upscope $end
$scope module OR2 $end
$var wire 1 = in0 $end
$var wire 1 < in1 $end
$var wire 1 B w_1 $end
$var wire 1 C w_0 $end
$var wire 1 % out $end
$scope module NAND $end
$var wire 1 % out $end
$var wire 1 B in1 $end
$var wire 1 C in0 $end
$upscope $end
$scope module NOT0 $end
$var wire 1 = in0 $end
$var wire 1 C out $end
$scope module NAND $end
$var wire 1 = in0 $end
$var wire 1 = in1 $end
$var wire 1 C out $end
$upscope $end
$upscope $end
$scope module NOT1 $end
$var wire 1 < in0 $end
$var wire 1 B out $end
$scope module NAND $end
$var wire 1 < in0 $end
$var wire 1 < in1 $end
$var wire 1 B out $end
$upscope $end
$upscope $end
$upscope $end
$upscope $end
$scope module OR0 $end
$var wire 1 & in0 $end
$var wire 1 % in1 $end
$var wire 1 D w_1 $end
$var wire 1 E w_0 $end
$var wire 1 - out $end
$scope module NAND $end
$var wire 1 - out $end
$var wire 1 D in1 $end
$var wire 1 E in0 $end
$upscope $end
$scope module NOT0 $end
$var wire 1 & in0 $end
$var wire 1 E out $end
$scope module NAND $end
$var wire 1 & in0 $end
$var wire 1 & in1 $end
$var wire 1 E out $end
$upscope $end
$upscope $end
$scope module NOT1 $end
$var wire 1 % in0 $end
$var wire 1 D out $end
$scope module NAND $end
$var wire 1 % in0 $end
$var wire 1 % in1 $end
$var wire 1 D out $end
$upscope $end
$upscope $end
$upscope $end
$upscope $end
$upscope $end
$enddefinitions $end
$comment Show the parameter values. $end
$dumpall
$end
#0
$dumpvars
1E
1D
1C
1B
1A
1@
1?
1>
0=
0<
1;
1:
19
18
17
16
05
04
13
12
11
10
1/
1.
0-
0,
0+
0*
0)
0(
0'
0&
0%
0$
0#
0"
0!
$end
#2
1!
#4
1"
0!
#6
1-
0E
1&
0;
15
07
1,
0.
1!
#8
0-
1E
0&
1;
05
17
0,
1.
1#
0"
0!
#10
1-
0E
1&
0;
0:
15
14
06
09
1+
0/
1!
#12
0D
1E
1%
0&
0C
1;
1:
1=
05
04
0?
16
19
1)
0+
01
1/
1"
0!
#14
0E
1&
0;
0:
15
14
07
06
09
1,
1+
0.
0/
1!
#16
0-
1D
1E
0%
0&
1C
1;
1:
0=
05
04
1?
17
16
19
0)
0,
0+
11
1.
1/
1$
0#
0"
0!
#18
1-
0E
1&
0:
14
08
1*
00
1!
#20
0D
1E
1%
0&
0C
0B
1:
1=
1<
04
0>
0A
18
1(
0*
02
10
1"
0!
#22
0E
1&
0;
0:
15
14
07
08
1,
1*
0.
00
1!
#24
1E
0&
1C
1;
1:
0=
05
04
0@
1>
1A
17
18
1'
0(
0,
0*
03
12
1.
10
1#
0"
0!
#26
0E
1&
0;
0:
15
14
06
09
08
1+
1*
0/
00
1!
#28
1E
0&
0C
1;
1:
1=
05
04
0?
0>
0A
16
19
18
1)
1(
0+
0*
01
02
1/
10
1"
0!
#30
0E
1&
0;
0:
15
14
07
06
09
08
1,
1+
1*
0.
0/
00
1!
