questions/base_logic.v
module CRUDE_AWAKENING(
     input wire       in0,
     output wire       out
);
    assign out = in0;
endmodule

module NAND_GATE(
     input wire       in0,
     input wire       in1,
     output wire       out
);
    assign out = ~ ( in0 & in1 );
endmodule

module NOT_GATE(
     input wire       in0,
     output wire       out
);
    NAND_GATE NAND(
        .in0    (in0    ),
        .in1    (in0    ),
        .out    (out    )
    );
endmodule

module AND_GATE(
     input wire       in0,
     input wire       in1,
     output wire       out
);
    wire w_1;
    NAND_GATE NAND(
        .in0    (in0    ),
        .in1    (in1    ),
        .out    (w_1    )
    );

    NOT_GATE NOT(
        .in0    (w_1    ),
        .out    (out    )
    );
    
endmodule

module NOR_GATE(
     input wire       in0,
     input wire       in1,
     output wire       out
);
    wire w_0;
    wire w_1;
    wire n_out;
    NOT_GATE NOT0(
        .in0    (in0    ),
        .out    (w_0    )
    );
    NOT_GATE NOT1(
        .in0    (in1    ),
        .out    (w_1    )
    );
    NAND_GATE NAND(
        .in0    (w_0    ),
        .in1    (w_1    ),
        .out    (n_out    )
    );
    NOT_GATE NOT(
        .in0    (n_out    ),
        .out    (out    )
    );
endmodule

module OR_GATE(
     input wire       in0,
     input wire       in1,
     output wire       out
);
    wire w_0;
    wire w_1;
    NOT_GATE NOT0(
        .in0    (in0    ),
        .out    (w_0    )
    );
    NOT_GATE NOT1(
        .in0    (in1    ),
        .out    (w_1    )
    );
    NAND_GATE NAND(
        .in0    (w_0    ),
        .in1    (w_1    ),
        .out    (out    )
    );
endmodule

module ALWAYS_ON_GATE(
     input wire       in0,
     output wire       out
);
    wire w_1;
    NOT_GATE NOT(
        .in0    (in0    ),
        .out    (w_1    )
    );
    OR_GATE OR(
        .in0    (in0    ),
        .in1    (w_1    ),
        .out    (out    )
    );
endmodule

module SECOND_TICK(
     input wire       in0,
     input wire       in1,
     output wire       out
);
    wire w_0;
    wire n_out;
    NOT_GATE NOT(
        .in0    (in1    ),
        .out    (w_0    )
    );
    AND_GATE AND(
        .in0    (w_0    ),
        .in1    (in0    ),
        .out    (out    )
    );
endmodule

module XOR_GATE(
     input wire       in0,
     input wire       in1,
     output wire       out
);
    wire w_0;
    wire w_1;
    
    NOR_GATE NOR0(
        .in0    (in0    ),
        .in1    (in1    ),
        .out    (w_0    )
    );

    AND_GATE AND(
        .in0    (in0    ),
        .in1    (in1    ),
        .out    (w_1    )
    );
    NOR_GATE NOR1(
        .in0    (w_0    ),
        .in1    (w_1    ),
        .out    (out    )
    );

    
endmodule

module BIGGER_OR_GATE(
     input wire       in0,
     input wire       in1,
     input wire       in2,
     output wire       out
);
    wire w_0;
    wire w_1;
    
    OR_GATE OR0(
        .in0    (in0    ),
        .in1    (in1    ),
        .out    (w_0    )
    );

    OR_GATE OR1(
        .in0    (in1    ),
        .in1    (in2    ),
        .out    (w_1    )
    );
    OR_GATE OR2(
        .in0    (w_0    ),
        .in1    (w_1    ),
        .out    (out    )
    );

    
endmodule

module BIGGER_AND_GATE(
     input wire       in0,
     input wire       in1,
     input wire       in2,
     output wire       out
);
    wire w_0;
    wire w_1;
    
    AND_GATE AND0(
        .in0    (in0    ),
        .in1    (in1    ),
        .out    (w_0    )
    );

    AND_GATE AND1(
        .in0    (in1    ),
        .in1    (in2    ),
        .out    (w_1    )
    );
    AND_GATE AND2(
        .in0    (w_0    ),
        .in1    (w_1    ),
        .out    (out    )
    );

endmodule

module XNOR_GATE(
     input wire       in0,
     input wire       in1,
     output wire       out
);
    wire n_out;
    XOR_GATE XOR(
        .in0    (in0    ),
        .in1    (in1    ),
        .out    (n_out    )
    );
    NOT_GATE NOT(
        .in0    (n_out    ),
        .out    (out    )
    );
endmodule

module SWITCH_GATE(
    input wire clk,
    input wire in0,
    input wire in1,
    output reg out
);

initial @ (posedge clk) begin
    if (in0 > 1'b0) begin
    assign out = in1;
    end else begin
    assign out = 1'b0;
    end
end

endmodule

module BYTE_SWITCH_GATE(
    input wire clk,
    input wire in0,
    input wire [7:0] in1,
    output reg [7:0] out
);
always @(posedge clk) begin
     if(in0>1'b0) begin 
        assign out = in1;
    end else begin
        assign out = 8'b00000000;
    end
end

endmodule

questions/MEMORY/05-INPUT-SELECTOR/impl.v
module MUX(
    input wire clk,
     input wire swc,
     input wire [7:0] in0,
     input wire [7:0] in1,
     output reg [7:0] out
);
wire w_0;
wire [7:0]w_1;
wire [7:0]w_2;
NOT_GATE NOT(
    .in0    (swc    ),
    .out    (w_0    )
);

BYTE_SWITCH_GATE BYTE_SWITCH_GATE_0(
    .clk    (clk    ),
    .in0    (swc    ),
    .in1    (in0    ),
    .out    (w_1    )
);


BYTE_SWITCH_GATE BYTE_SWITCH_GATE_1(
    .clk    (clk    ),
    .in0    (w_0    ),
    .in1    (in1    ),
    .out    (w_2    )
);
always @(posedge clk) begin
      if (swc > 1'b0) begin
        assign out = w_1;
        end else begin
        assign out = w_2;
        end 
end

endmodule

questions/MEMORY/06-1-THE-BUS/impl.v
module BUS(
    input wire clk,
    input wire from,
    input wire to,
    input wire [7:0] in0,
    input wire [7:0] in1,
    output wire [7:0] out0,
    output wire [7:0] out1
);

wire nfrom;
wire nto;
wire [7:0]w_0;
wire [7:0]w_1;
wire [7:0]w_2;

NOT_GATE NOT_1(
    .in0    (to    ),
    .out    (nto    )
);

MUX MUX0(
    .clk    (clk    ),
    .swc (from),
    .in0 (in0),
    .in1 (in1),
    .out (w_0)
);

BYTE_SWITCH_GATE SWC0(
    .clk    (clk    ),
    .in0 (to),
    .in1(w_0),
    .out(out0)
);

BYTE_SWITCH_GATE SWC1(
    .clk    (clk    ),
    .in0 (nto),
    .in1(w_0),
    .out(out1)
);
endmodule

questions/MEMORY/06-1-THE-BUS/tb.v
module BUS_tb;
    reg clk = 1'b0;
    reg from = 1'b0;
    reg to = 1'b0;
    reg    [7:0]    in0 = 8'h00;
    reg    [7:0]    in1 = 8'h00;
    wire   [7:0]    out;
    wire out0 = 8'h00;
    wire out1 = 8'h00;
    
initial begin
        $dumpfile("wave.vcd");
        $dumpvars(0, DUT);
    end
    
   always #1 begin
        clk <= ~clk;
    end
    BUS DUT(
        .clk    (clk    ),
        .from    (from    ),
        .to    (to    ),
        .in0    (in0    ),
        .in1    (in1    ),
        .out1    (out1    ),
        .out0    (out0    )
    );
    
    initial begin
        #2
        in0 = 8'ha1;
        in1 = 8'h02;
        #2
        from = 1'b1;
        #2
        from = 1'b0;
        #2
      to = 1'b1;
        #2
       to = 1'b0;
        #2
        $finish;
    end
endmodule

questions/MEMORY/06-1-THE-BUS/wave.vcd
$date
	Fri Apr 26 12:33:56 2024
$end
$version
	Icarus Verilog
$end
$timescale
	1s
$end
$scope module BUS_tb $end
$scope module DUT $end
$var wire 1 ! clk $end
$var wire 1 " from $end
$var wire 8 # in0 [7:0] $end
$var wire 8 $ in1 [7:0] $end
$var wire 1 % to $end
$var wire 8 & w_0 [7:0] $end
$var wire 8 ' out1 [7:0] $end
$var wire 8 ( out0 [7:0] $end
$var wire 1 ) nto $end
$scope module MUX0 $end
$var wire 1 ! clk $end
$var wire 8 * in0 [7:0] $end
$var wire 8 + in1 [7:0] $end
$var wire 1 " swc $end
$var wire 8 , w_2 [7:0] $end
$var wire 8 - w_1 [7:0] $end
$var wire 1 . w_0 $end
$var reg 8 / out [7:0] $end
$scope module BYTE_SWITCH_GATE_0 $end
$var wire 1 ! clk $end
$var wire 1 " in0 $end
$var wire 8 0 in1 [7:0] $end
$var reg 8 1 out [7:0] $end
$upscope $end
$scope module BYTE_SWITCH_GATE_1 $end
$var wire 1 ! clk $end
$var wire 8 2 in1 [7:0] $end
$var wire 1 . in0 $end
$var reg 8 3 out [7:0] $end
$upscope $end
$scope module NOT $end
$var wire 1 " in0 $end
$var wire 1 . out $end
$scope module NAND $end
$var wire 1 " in0 $end
$var wire 1 " in1 $end
$var wire 1 . out $end
$upscope $end
$upscope $end
$upscope $end
$scope module NOT_1 $end
$var wire 1 % in0 $end
$var wire 1 ) out $end
$scope module NAND $end
$var wire 1 % in0 $end
$var wire 1 % in1 $end
$var wire 1 ) out $end
$upscope $end
$upscope $end
$scope module SWC0 $end
$var wire 1 ! clk $end
$var wire 1 % in0 $end
$var wire 8 4 in1 [7:0] $end
$var reg 8 5 out [7:0] $end
$upscope $end
$scope module SWC1 $end
$var wire 1 ! clk $end
$var wire 1 ) in0 $end
$var wire 8 6 in1 [7:0] $end
$var reg 8 7 out [7:0] $end
$upscope $end
$upscope $end
$upscope $end
$enddefinitions $end
$comment Show the parameter values. $end
$dumpall
$end
#0
$dumpvars
bx 7
bx 6
bx 5
bx 4
bx 3
b0 2
bx 1
b0 0
bx /
1.
bx -
bx ,
b0 +
b0 *
1)
bx (
bx '
bx &
0%
b0 $
b0 #
0"
0!
$end
#1
b0 -
b0 1
b0 '
b0 7
b0 &
b0 /
b0 4
b0 6
b0 ,
b0 3
b0 (
b0 5
1!
#2
0!
b10 '
b10 7
b10 &
b10 /
b10 4
b10 6
b10 ,
b10 3
b10 $
b10 +
b10 2
b10100001 #
b10100001 *
b10100001 0
#3
1!
#4
0!
0.
1"
#5
b10100001 -
b10100001 1
b0 ,
b0 3
b10100001 '
b10100001 7
b10100001 &
b10100001 /
b10100001 4
b10100001 6
1!
#6
0!
1.
0"
#7
b10 ,
b10 3
b10 '
b10 7
b10 &
b10 /
b10 4
b10 6
b0 -
b0 1
1!
#8
0!
0)
1%
#9
b10 (
b10 5
b0 '
b0 7
1!
#10
0!
1)
0%
#11
b10 '
b10 7
b0 (
b0 5
1!
