questions/base_logic.v
module CRUDE_AWAKENING(
     input wire       in0,
     output wire       out
);
    assign out = in0;
endmodule

module NAND_GATE(
     input wire       in0,
     input wire       in1,
     output wire       out
);
    assign out = ~ ( in0 & in1 );
endmodule

module NOT_GATE(
     input wire       in0,
     output wire       out
);
    NAND_GATE NAND(
        .in0    (in0    ),
        .in1    (in0    ),
        .out    (out    )
    );
endmodule

module AND_GATE(
     input wire       in0,
     input wire       in1,
     output wire       out
);
    wire w_1;
    NAND_GATE NAND(
        .in0    (in0    ),
        .in1    (in1    ),
        .out    (w_1    )
    );

    NOT_GATE NOT(
        .in0    (w_1    ),
        .out    (out    )
    );
    
endmodule

module NOR_GATE(
     input wire       in0,
     input wire       in1,
     output wire       out
);
    wire w_0;
    wire w_1;
    wire n_out;
    NOT_GATE NOT0(
        .in0    (in0    ),
        .out    (w_0    )
    );
    NOT_GATE NOT1(
        .in0    (in1    ),
        .out    (w_1    )
    );
    NAND_GATE NAND(
        .in0    (w_0    ),
        .in1    (w_1    ),
        .out    (n_out    )
    );
    NOT_GATE NOT(
        .in0    (n_out    ),
        .out    (out    )
    );
endmodule

module OR_GATE(
     input wire       in0,
     input wire       in1,
     output wire       out
);
    wire w_0;
    wire w_1;
    NOT_GATE NOT0(
        .in0    (in0    ),
        .out    (w_0    )
    );
    NOT_GATE NOT1(
        .in0    (in1    ),
        .out    (w_1    )
    );
    NAND_GATE NAND(
        .in0    (w_0    ),
        .in1    (w_1    ),
        .out    (out    )
    );
endmodule

module ALWAYS_ON_GATE(
     input wire       in0,
     output wire       out
);
    wire w_1;
    NOT_GATE NOT(
        .in0    (in0    ),
        .out    (w_1    )
    );
    OR_GATE OR(
        .in0    (in0    ),
        .in1    (w_1    ),
        .out    (out    )
    );
endmodule

module SECOND_TICK(
     input wire       in0,
     input wire       in1,
     output wire       out
);
    wire w_0;
    wire n_out;
    NOT_GATE NOT(
        .in0    (in1    ),
        .out    (w_0    )
    );
    AND_GATE AND(
        .in0    (w_0    ),
        .in1    (in0    ),
        .out    (out    )
    );
endmodule

module XOR_GATE(
     input wire       in0,
     input wire       in1,
     output wire       out
);
    wire w_0;
    wire w_1;
    
    NOR_GATE NOR0(
        .in0    (in0    ),
        .in1    (in1    ),
        .out    (w_0    )
    );

    AND_GATE AND(
        .in0    (in0    ),
        .in1    (in1    ),
        .out    (w_1    )
    );
    NOR_GATE NOR1(
        .in0    (w_0    ),
        .in1    (w_1    ),
        .out    (out    )
    );

    
endmodule

module BIGGER_OR_GATE(
     input wire       in0,
     input wire       in1,
     input wire       in2,
     output wire       out
);
    wire w_0;
    wire w_1;
    
    OR_GATE OR0(
        .in0    (in0    ),
        .in1    (in1    ),
        .out    (w_0    )
    );

    OR_GATE OR1(
        .in0    (in1    ),
        .in1    (in2    ),
        .out    (w_1    )
    );
    OR_GATE OR2(
        .in0    (w_0    ),
        .in1    (w_1    ),
        .out    (out    )
    );

    
endmodule

module BIGGER_AND_GATE(
     input wire       in0,
     input wire       in1,
     input wire       in2,
     output wire       out
);
    wire w_0;
    wire w_1;
    
    AND_GATE AND0(
        .in0    (in0    ),
        .in1    (in1    ),
        .out    (w_0    )
    );

    AND_GATE AND1(
        .in0    (in1    ),
        .in1    (in2    ),
        .out    (w_1    )
    );
    AND_GATE AND2(
        .in0    (w_0    ),
        .in1    (w_1    ),
        .out    (out    )
    );

endmodule

module XNOR_GATE(
     input wire       in0,
     input wire       in1,
     output wire       out
);
    wire n_out;
    XOR_GATE XOR(
        .in0    (in0    ),
        .in1    (in1    ),
        .out    (n_out    )
    );
    NOT_GATE NOT(
        .in0    (n_out    ),
        .out    (out    )
    );
endmodule

module SWITCH_GATE(
    input wire clk,
    input wire in0,
    input wire in1,
    output reg out
);

always @ (posedge clk) begin
    if (in0 > 1'b0) begin
    out <= in1;
    end else begin
    out <= 1'b0;
    end
end

endmodule

module BYTE_SWITCH_GATE(
    input wire clk,
    input wire in0,
    input wire [7:0] in1,
    output reg [7:0] out
);
always @(posedge clk) begin
     if(in0>1'b0) begin 
         out <= in1;
    end else begin
         out <= 8'b00000000;
    end
end

endmodule

questions/MEMORY/02-DELAYED-LINES/impl.v
module DELAY(
        input wire clk,
        input wire rst,
        input wire i_data,
        output wire o_data
);

        reg r_data;

        assign o_data = r_data;

        always @(posedge clk) begin
                if(rst) begin
                        r_data <= 1'b0;
                end else begin
                        r_data <= i_data;
                end
        end

endmodule
module DELAY_LINES (
    input wire clk,
     input wire       in0,
     output wire       out
);
DELAY DELAY_0(
    .clk(clk),
    .rst(1'b0),
    .i_data(in0),
    .o_data(w_0)
);
DELAY DELAY_1(
    .clk(clk),
    .rst(1'b0),
    .i_data(w_0),
    .o_data(out)
);

endmodule

questions/MEMORY/06-2-SAVING-GRACEFULLY/impl.v
module MEMORY(
    input wire clk,
     input wire       save,
     input wire         value,
     output wire       out
);
    SWITCH_GATE SWC0(
        .clk(clk),
        .in0    (save    ),
        .in1    (value    ),
        .out    (w_1    )
    );
    NOT_GATE NOT0(
        .in0    (save    ),
        .out    (nsave    )
    );
    OR_GATE OR0(
        .in0    (w_1    ),
        .in1    (w_0    ),
        .out    (w_2    )
    );
    DELAY DELAY0(
        .clk    (clk    ),
        .rst    (1'b0    ),
        .i_data    (w_2    ),
        .o_data    (w_3    )
    );
    SWITCH_GATE SWC1(
        .clk(clk),
        .in0    (nsave    ),
        .in1    (w_3    ),
        .out    (w_0    )
    );
assign out = w_3;
endmodule

questions/MEMORY/06-2-SAVING-GRACEFULLY/tb.v

module MEMORY_tb;

    reg save = 1'b0;
    reg value = 1'b0;
    reg clk = 1'b1;
    initial begin
        $dumpfile("wave.vcd");
        $dumpvars(0, DUT);
    end
    always #1 begin
        clk <= ~clk;
    end
    MEMORY DUT(
        .clk (clk),
        .save    (save    ),
        .value    (value    ),
        .out    (out    )
    );

    initial begin
        save = 1'b1;
        value = 1'b1;
        #4
        value = 1'b0;
        #4
        save = 1'b0;
        #2
        save = 1'b0;
        #2
        value = 1'b1;
        #2
        save = 1'b1;
        value = 1'b0;
        #2
        value = 1'b1;
        #4
        save = 1'b0;
        #2
        value = 1'b0;
        #2
        save = 1'b1;
        #4
        $finish;
    end

endmodule

questions/MEMORY/06-2-SAVING-GRACEFULLY/wave.vcd
$date
	Tue Apr 30 10:47:11 2024
$end
$version
	Icarus Verilog
$end
$timescale
	1s
$end
$scope module MEMORY_tb $end
$scope module DUT $end
$var wire 1 ! clk $end
$var wire 1 " out $end
$var wire 1 # save $end
$var wire 1 $ value $end
$var wire 1 % w_3 $end
$var wire 1 & w_2 $end
$var wire 1 ' w_1 $end
$var wire 1 ( w_0 $end
$var wire 1 ) nsave $end
$scope module DELAY0 $end
$var wire 1 ! clk $end
$var wire 1 * rst $end
$var wire 1 % o_data $end
$var wire 1 & i_data $end
$var reg 1 % r_data $end
$upscope $end
$scope module NOT0 $end
$var wire 1 # in0 $end
$var wire 1 ) out $end
$scope module NAND $end
$var wire 1 # in0 $end
$var wire 1 # in1 $end
$var wire 1 ) out $end
$upscope $end
$upscope $end
$scope module OR0 $end
$var wire 1 + w_1 $end
$var wire 1 , w_0 $end
$var wire 1 & out $end
$var wire 1 ( in1 $end
$var wire 1 ' in0 $end
$scope module NAND $end
$var wire 1 & out $end
$var wire 1 + in1 $end
$var wire 1 , in0 $end
$upscope $end
$scope module NOT0 $end
$var wire 1 , out $end
$var wire 1 ' in0 $end
$scope module NAND $end
$var wire 1 , out $end
$var wire 1 ' in1 $end
$var wire 1 ' in0 $end
$upscope $end
$upscope $end
$scope module NOT1 $end
$var wire 1 + out $end
$var wire 1 ( in0 $end
$scope module NAND $end
$var wire 1 + out $end
$var wire 1 ( in1 $end
$var wire 1 ( in0 $end
$upscope $end
$upscope $end
$upscope $end
$scope module SWC0 $end
$var wire 1 ! clk $end
$var wire 1 # in0 $end
$var wire 1 $ in1 $end
$var reg 1 ' out $end
$upscope $end
$scope module SWC1 $end
$var wire 1 ! clk $end
$var wire 1 ) in0 $end
$var wire 1 % in1 $end
$var reg 1 ( out $end
$upscope $end
$upscope $end
$upscope $end
$enddefinitions $end
$comment Show the parameter values. $end
$dumpall
$end
#0
$dumpvars
0,
1+
0*
0)
0(
1'
1&
x%
1$
1#
x"
1!
$end
#1
0!
#2
1"
1%
1!
#3
0!
#4
0&
1,
0'
1!
0$
#5
0!
#6
0"
0%
1!
#7
0!
#8
1!
1)
0#
#9
0!
#10
1!
#11
0!
#12
1!
1$
#13
0!
#14
1!
0)
0$
1#
#15
0!
#16
1&
0,
1'
1!
1$
#17
0!
#18
1"
1%
1!
#19
0!
#20
1,
0+
0'
1(
1!
1)
0#
#21
0!
#22
1!
0$
#23
0!
#24
0&
1+
0(
1!
0)
1#
#25
0!
#26
0"
0%
1!
