questions/MEMORY/02-DELAYED-LINES/impl.v
module DELAY(
    input wire clk,
     input wire       in0,
     output reg       out
);
reg w_0 = 1'b0;
reg w_1 = 1'b0;
reg w_2 = 1'b0;
always @(posedge clk) begin
    if(w_0 > 1'b0)begin
        assign w_0 = 1'b0;
        assign w_1 = in0;
        assign out = w_2;
    end else begin
        assign w_0 = 1'b1;
        assign w_2 = in0;
        assign out = w_1;
    end
end
endmodule

module DELAY_LINES (
    input wire clk,
     input wire       in0,
     output wire       out
);
DELAY DELAY_0(
    .clk(clk),
    .in0(in0),
    .out(w_0)
);
DELAY DELAY_1(
    .clk(clk),
    .in0(w_0),
    .out(out)
);

endmodule

questions/MEMORY/02-DELAYED-LINES/tb.v

module DELAY_tb;

    reg in0 = 1'b0;
    initial begin
        $dumpfile("wave.vcd");
        $dumpvars(0, DUT);
    end
    wire out;

  
   
    DELAY_LINES DUT(
        .in0    (in0    ),
        .out    (out    )
    );

    initial begin
        in0 = 1'b0;
        #2
        in0 = 1'b1;
        #2
        in0 = 1'b0;
        #3       
        in0 = 1'b1;
        #3       
        in0 = 1'b0;
        #2
        $finish;
    end

endmodule

questions/MEMORY/02-DELAYED-LINES/wave.vcd
$date
	Fri Apr 26 15:23:50 2024
$end
$version
	Icarus Verilog
$end
$timescale
	1s
$end
$scope module DELAY_tb $end
$scope module DUT $end
$var wire 1 ! clk $end
$var wire 1 " in0 $end
$var wire 1 # w_0 $end
$var wire 1 $ out $end
$scope module DELAY_0 $end
$var wire 1 ! clk $end
$var wire 1 " in0 $end
$var reg 1 # out $end
$var reg 1 % w_0 $end
$var reg 1 & w_1 $end
$var reg 1 ' w_2 $end
$upscope $end
$scope module DELAY_1 $end
$var wire 1 ! clk $end
$var wire 1 # in0 $end
$var reg 1 $ out $end
$var reg 1 ( w_0 $end
$var reg 1 ) w_1 $end
$var reg 1 * w_2 $end
$upscope $end
$upscope $end
$upscope $end
$enddefinitions $end
$comment Show the parameter values. $end
$dumpall
$end
#0
$dumpvars
0*
0)
0(
0'
0&
0%
x$
x#
0"
0!
$end
#1
0#
1%
0$
0*
1(
1!
#2
0!
1'
1"
#3
1$
1)
0(
1*
1#
1&
0%
1!
#4
0!
#5
1%
1(
1!
#6
0!
#7
0(
0%
1!
0$
0)
0*
0#
0&
0'
0"
#8
0!
#9
1%
1(
1!
#10
0!
#11
0(
0%
1!
