questions/MEMORY/02-DELAYED-LINES/impl.v
module DELAY(
     input wire       in0,
     output reg       out = 1'b0
);
always @(in0) begin
    #1
  out = in0;
end
endmodule

module DELAY_LINES (
     input wire       in0,
     output wire       out
);
DELAY DELAY_0(
    .in0(in0),
    .out( w_0)
);
DELAY DELAY_1(
    .in0(w_0),
    .out(out)
);

endmodule

questions/MEMORY/02-DELAYED-LINES/tb.v

module DELAY_tb;

    reg in0 = 1'b0;
    initial begin
        $dumpfile("wave.vcd");
        $dumpvars(0, DUT);
    end
    wire out;

  
   
    DELAY_LINES DUT(
        .in0    (in0    ),
        .out    (out    )
    );

    initial begin
        in0 = 1'b0;
        #2
        in0 = 1'b1;
        #2
        in0 = 1'b0;
        #3       
        in0 = 1'b1;
        #3       
        in0 = 1'b0;
        #2
        $finish;
    end

endmodule

questions/MEMORY/02-DELAYED-LINES/wave.vcd
$date
	Sun Apr 21 17:23:27 2024
$end
$version
	Icarus Verilog
$end
$timescale
	1s
$end
$scope module DELAY_tb $end
$scope module DUT $end
$var wire 1 ! in0 $end
$var wire 1 " w_0 $end
$var wire 1 # out $end
$scope module DELAY_0 $end
$var wire 1 ! in0 $end
$var reg 1 " out $end
$upscope $end
$scope module DELAY_1 $end
$var wire 1 " in0 $end
$var reg 1 # out $end
$upscope $end
$upscope $end
$upscope $end
$enddefinitions $end
$comment Show the parameter values. $end
$dumpall
$end
#0
$dumpvars
0#
0"
0!
$end
#2
1!
#3
1"
#4
1#
0!
#5
0"
#6
0#
#7
1!
#8
1"
#9
1#
#10
0!
#11
0"
#12
0#
